{
    "@context": "dtmi:dtdl:context;2",
    "@id": "dtmi:com:adt:flightintoazure:airplane;1",
    "@type": "Interface",
    "displayName": "Airplane - Flight Into Azure - Interface Model",
    "contents": [
        {
            "@type": "Telemetry",
            "name": "callsign",
            "schema": "string"
        },
        {
            "@type": "Telemetry",
            "name": "date",
            "schema": "string"
        },
        {
            "@type": "Telemetry",
            "name": "time",
            "schema": "string"
        },        
        {
            "@type": "Telemetry",
            "name": "dateTimeUtc",
            "schema": "dateTime"
        },
        {
            "@type": "Telemetry",
            "name": "position",
            "schema": "string"
        },        
        {
            "@type": "Telemetry",
            "name": "latitude",
            "schema": "double"
        },
        {
            "@type": "Telemetry",
            "name": "longitude",
            "schema": "double"
        },
        {
            "@type": "Telemetry",
            "name": "altitude",
            "schema": "double"
        },
        {
            "@type": "Telemetry",
            "name": "vSFPM",
            "schema": "double"
        },
        {
            "@type": "Telemetry",
            "name": "secondsLastReport",
            "schema": "double"
        },
        {
            "@type": "Telemetry",
            "name": "speed",
            "schema": "double"
        },
        {
            "@type": "Telemetry",
            "name": "direction",
            "schema": "double"
        },
        {
            "@type": "Telemetry",
            "name": "outsideAirTemp",
            "schema": "double"
        },
        {
            "@type": "Telemetry",
            "name": "windDirection",
            "schema": "double"
        },
        {
            "@type": "Telemetry",
            "name": "windSpeed",
            "schema": "double"
        },
        {
            "@type": "Property",
            "name": "lastCallsign",
            "description": "Call sign",
            "schema": "string",
            "writable": true
        },
        {
            "@type": "Property",
            "name": "lastDate",
            "description": "Date",
            "schema": "string",
            "writable": true
        },
        {
            "@type": "Property",
            "name": "lastTime",
            "description": "Time",
            "schema": "string",
            "writable": true
        },        
        {
            "@type": "Property",
            "name": "lastDateTimeUtc",
            "description": "Datetime UTC",
            "schema": "dateTime",
            "writable": true
        },
        {
            "@type": "Property",
            "name": "lastPosition",
            "description": "Position",
            "schema": "string",
            "writable": true
        },        
        {
            "@type": "Property",
            "name": "lastLatitude",
            "description": "Latitude",
            "schema": "double",
            "writable": true
        },
        {
            "@type": "Property",
            "name": "lastLongitude",
            "description": "Longitude",
            "schema": "double",
            "writable": true
        },
        {
            "@type": "Property",
            "name": "lastAltitude",
            "description": "Altitude",
            "schema": "double",
            "writable": true
        },
        {
            "@type": "Property",
            "name": "lastVSFPM",
            "description": "Vertical speed in feet per minute",
            "schema": "double",
            "writable": true
        },
        {
            "@type": "Property",
            "name": "lastSecondsLastReport",
            "description": "Seconds to last report",
            "schema": "double",
            "writable": true
        },
        {
            "@type": "Property",
            "name": "lastSpeed",
            "description": "Speed",
            "schema": "double",
            "writable": true
        },
        {
            "@type": "Property",
            "name": "lastDirection",
            "description": "Direction",
            "schema": "double",
            "writable": true
        },
        {
            "@type": [
                "Property",
                "Temperature"
            ],
            "name": "lastOutsideAirTemp",
            "description": "Outside air temperature",
            "schema": "double",
            "unit": "degreeFahrenheit",
            "writable": true
        },
        {
            "@type": "Property",
            "name": "lastWindDirection",
            "description": "Win direction",
            "schema": "double",
            "writable": true
        },
        {
            "@type": "Property",
            "name": "lastWindSpeed",
            "description": "Wind speed",
            "schema": "double",
            "writable": true
        }
   ]
}